{
  "covers": [
    {"title": "PAYSAGE", "imageUrl": "../../assets/images/En_couverture/Couverture_paysage.jpg"},
    {"title": "ARCHITECTURE", "imageUrl": "This is projet 2"},
    {"title": "MOBILIER", "imageUrl": "This is projet 3"},
    {"title": "VISUELS 3D", "imageUrl": "This is projet 4"}
  ],
  "projects": {
    "architecture": 
      [
        {"title": "Rénovation & aménagement d'une maison sur 3 niveaux.", "content": ["Combles", "Chambre parentale", "Combles", "Pièce de vie", "Plan 2D et 3D", "WC", "Salle d'eau"]},
        {"title": "Aménagement d'un hall d'accueil pour une association.", "content": ["", "", "Enseigne lumineuse", "Croquis 3D & Plan"]},
        {"title": "Aménagement d'un ancien pressoir en habitation.", "content": ["Façade", "Cuisine", "Chambre"]},
        {"title": "Aménagement intérieur d'une maison Rochelaise.", "content": ["Cuisine", "Plan/croquis du 1er étage", "Chambre", "Véranda et jardin", "Espace bibliothèque"]},
        {"title": "Projet construction d'un logement aux Sorinières.", "content": [""]}
      ],
    "mobilier":
      [
        {"title": "Petit dressing et rangement pour une chambre d'enfant sous pente.", "content": ""},
        {"title": "Petit dressing et rangement pour une chambre d'enfant sous pente2.", "content": ""},
        {"title": "Petit dressing et rangement pour une chambre d'enfant sous pente3.", "content": ""},
        {"title": "Petit dressing et rangement pour une chambre d'enfant sous pente4.", "content": ""},
        {"title": "Meuble étagères et rangement avec petite tablette bureau.", "content": ""},
        {"title": "Conception de différents types d'espace de travail pour le lycée expérimental de Saint Nazaire.", "content": ""},
        {"title": "Salle d'eau d'une chambre parentale.", "content": ""},
        {"title": "Espace vestiaire pour l'entrée d'une maison.", "content": ""}
      ],
    "paysage": 
      [
        {"title": "Projet d'aménagement d'une placette et d'une aire de jeux.", "content": ""},
        {"title": "Aménagement d'un jardin privé. Planche d'ambiance et croquis.", "content": ""},
        {"title": "Aménagement d'un jardin privé. Schéma directeur et palette végétale pour massif.", "content": ""}
      ],
    "visuels_3d": 
      [
        {"title": "Complexe hôtelier.", "content": ""},
        {"title": "Lycée expérimental - Espaces communs.", "content": ""},
        {"title": "Réception d'un ERP.", "content": ""},
        {"title": "Espace aquatique d'un camping.", "content": ""},
        {"title": "Bâtiment d'entreprise.", "content": ""},
        {"title": "Constructeur - Bâtiment existant transformé en 4 logements indépendants.", "content": ""}
      ]
  }
}